databricksbundle/DatabricksBundle.py
databricksbundle/DatabricksBundleTest.py
databricksbundle/_config/config.yaml
databricksbundle/_config/config_test_aws.yaml
databricksbundle/_config/config_test_azure.yaml
databricksbundle/_config/databricks/databricks_connect.yaml
databricksbundle/_config/databricks/databricks_notebook.yaml
databricksbundle/_config/databricks/databricks_script.yaml
databricksbundle/bootstrap/package_config_reader.py
databricksbundle/dbutils/DatabricksConnectDbUtilsFactory.py
databricksbundle/dbutils/DatabricksDbUtilsFactory.py
databricksbundle/dbutils/DbUtilsMock.py
databricksbundle/dbutils/DbUtilsWrapper.py
databricksbundle/dbutils/DbUtilsWrapperTest.py
databricksbundle/dbutils/IPythonDbUtilsResolver.py
databricksbundle/detector.py
databricksbundle/detector_test.py
databricksbundle/filesystem/DbUtilsFilesystem.py
databricksbundle/notebook/DataFrameDisplay.py
databricksbundle/notebook/GithubLinkGenerator.py
databricksbundle/notebook/NotebookErrorHandler.py
databricksbundle/notebook/PandasDataFrameDisplay.py
databricksbundle/notebook/helpers.py
databricksbundle/notebook/logger/NotebookLoggerFactory.py
databricksbundle/notebook/path/DatabricksNotebookPathResolver.py
databricksbundle/notebook/path/DatabricksScriptPathResolver.py
databricksbundle/notebook/path/LocalScriptPathResolver.py
databricksbundle/notebook/path/NotebookPathResolverInterface.py
databricksbundle/spark/DatabricksConnectSessionFactory.py
databricksbundle/spark/NotebookSessionFactory.py
databricksbundle/spark/ScriptSessionFactory.py
databricksbundle/spark/SparkSessionLazy.py
databricksbundle/spark/config/ConfiguratorInterface.py
databricksbundle/spark/config/DictConfigConfigurator.py
databricksbundle/spark/existing_spark_cleanup.py
databricksbundle/spark/hadoop_home_setter.py
databricksbundle/spark/java_home_setter.py
databricksbundle/storage/StorageConfigurator.py
databricksbundle/storage/StorageConfiguratorInterface.py
databricksbundle/storage/StorageConfiguratorTest.py
databricks_bundle-1.5.1.dist-info/LICENSE
databricks_bundle-1.5.1.dist-info/METADATA
databricks_bundle-1.5.1.dist-info/WHEEL
databricks_bundle-1.5.1.dist-info/entry_points.txt
databricks_bundle-1.5.1.dist-info/RECORD
