Metadata-Version: 2.1
Name: databricks-bundle
Version: 1.5.1
Summary: [DEPRECATED] Databricks runtime support for the Daipe framework
Home-page: https://github.com/daipe-ai/databricks-bundle
License: MIT
Author: Jiri Koutny
Author-email: jiri.koutny@datasentics.com
Requires-Python: >=3.8,<4.0
Classifier: Development Status :: 7 - Inactive
Classifier: License :: OSI Approved :: MIT License
Classifier: Operating System :: OS Independent
Classifier: Programming Language :: Python :: 3
Classifier: Programming Language :: Python :: 3.8
Classifier: Programming Language :: Python :: 3.9
Classifier: Programming Language :: Python :: 3.10
Classifier: Programming Language :: Python :: 3.11
Classifier: Programming Language :: Python :: 3.12
Classifier: Programming Language :: Python :: 3.13
Requires-Dist: console-bundle (>=0.5,<0.6)
Requires-Dist: daipe-core (>=1.4.4,<2.0.0)
Requires-Dist: injecta (==0.10.*)
Requires-Dist: logger-bundle (==0.7.*)
Requires-Dist: pyfony-bundles (==0.4.*)
Requires-Dist: pyfony-core (==0.8.*)
Requires-Dist: pyspark-bundle (>=1.2,<2.0)
Project-URL: Repository, https://github.com/daipe-ai/databricks-bundle
